CobraRouter/__init__.py
CobraRouter/detect.py
CobraRouter/main.py
CobraRouter/router/__init__.py
CobraRouter/router/_main.py
CobraRouter/router/_swaps.py
CobraRouter/router/PumpSwapAMM/PumpSwapAMM.py
CobraRouter/router/PumpSwapAMM/__init__.py
CobraRouter/router/PumpSwapAMM/fetch_reserves.py
CobraRouter/router/libutils/__init__.py
CobraRouter/router/libutils/_common.py
CobraRouter/router/libutils/cleaner.py
CobraRouter/router/libutils/colors.py
CobraRouter/router/meteoraDBC/__init__.py
CobraRouter/router/meteoraDBC/meteora.py
CobraRouter/router/meteoraDBC/pool.py
CobraRouter/router/meteoraDBC/state.py
CobraRouter/router/meteoraDBC/swap.py
CobraRouter/router/meteora_damm_v1/__init__.py
CobraRouter/router/meteora_damm_v1/damm_core.py
CobraRouter/router/meteora_damm_v1/damm_swap.py
CobraRouter/router/meteora_damm_v2/__init__.py
CobraRouter/router/meteora_damm_v2/damm2_core.py
CobraRouter/router/meteora_damm_v2/damm2_swap.py
CobraRouter/router/meteora_dlmm/__init__.py
CobraRouter/router/meteora_dlmm/dlmm_bin.py
CobraRouter/router/meteora_dlmm/dlmm_core.py
CobraRouter/router/meteora_dlmm/dlmm_swap.py
CobraRouter/router/pump_fun/__init__.py
CobraRouter/router/pump_fun/migration_source.py
CobraRouter/router/pump_fun/pump_bond.py
CobraRouter/router/pump_fun/pump_fun.py
CobraRouter/router/raydiumswap/__init__.py
CobraRouter/router/raydiumswap/setup.py
CobraRouter/router/raydiumswap/amm_v4/__init__.py
CobraRouter/router/raydiumswap/amm_v4/v4_amm_api.py
CobraRouter/router/raydiumswap/amm_v4/v4_amm_core.py
CobraRouter/router/raydiumswap/amm_v4/v4_amm_swap.py
CobraRouter/router/raydiumswap/clmm/__init__.py
CobraRouter/router/raydiumswap/clmm/clmm_core.py
CobraRouter/router/raydiumswap/clmm/clmm_swap.py
CobraRouter/router/raydiumswap/clmm/raydium_apiv3.py
CobraRouter/router/raydiumswap/clmm/ticks.py
CobraRouter/router/raydiumswap/cpmm/__init__.py
CobraRouter/router/raydiumswap/cpmm/cpmm_core.py
CobraRouter/router/raydiumswap/cpmm/cpmm_swap.py
cobra_router-0.42.0.9.dist-info/METADATA
cobra_router-0.42.0.9.dist-info/WHEEL
cobra_router-0.42.0.9.dist-info/top_level.txt
cobra_router-0.42.0.9.dist-info/RECORD
