Metadata-Version: 2.1
Name: cobra-router
Version: 0.42.0.9
Summary: Cobra Router
Home-page: https://github.com/FLOCK4H/Cobra
Author: FLOCK4H
Classifier: Programming Language :: Python :: 3
Classifier: Operating System :: OS Independent
Requires-Python: >=3.7
Requires-Dist: construct
Requires-Dist: solana
Requires-Dist: solders
Requires-Dist: requests
Requires-Dist: asyncio
Requires-Dist: aiohttp
Requires-Dist: httpx
Requires-Dist: base58
Requires-Dist: readchar
Requires-Dist: dotenv
Requires-Dist: python-telegram-bot
Requires-Dist: asyncpg
